epde/__init__.py
epde/decorators.py
epde/eq_mo_objectives.py
epde/evaluators.py
epde/globals.py
epde/supplementary.py
epde/cache/__init__.py
epde/cache/cache.py
epde/interface/__init__.py
epde/interface/equation_translator.py
epde/interface/interface.py
epde/interface/logger.py
epde/interface/prepared_tokens.py
epde/interface/solver_integration.py
epde/interface/token_family.py
epde/interface/type_checks.py
epde/operators/__init__.py
epde/operators/common/__init__.py
epde/operators/common/coeff_calculation.py
epde/operators/common/fitness.py
epde/operators/common/right_part_selection.py
epde/operators/common/sparsity.py
epde/operators/multiobjective/__init__.py
epde/operators/multiobjective/moeadd_specific.py
epde/operators/multiobjective/mutations.py
epde/operators/multiobjective/selections.py
epde/operators/multiobjective/variation.py
epde/operators/singleobjective/__init__.py
epde/operators/singleobjective/ea_stop_criteria.py
epde/operators/singleobjective/mutations.py
epde/operators/singleobjective/selections.py
epde/operators/singleobjective/so_specific.py
epde/operators/singleobjective/variation.py
epde/operators/utils/__init__.py
epde/operators/utils/default_parameter_loader.py
epde/operators/utils/operator_mappers.py
epde/operators/utils/template.py
epde/operators/utils/parameters/__init__.py
epde/operators/utils/parameters/default_parameters_multi_objective.json
epde/operators/utils/parameters/default_parameters_single_objective.json
epde/optimizers/__init__.py
epde/optimizers/blocks.py
epde/optimizers/builder.py
epde/optimizers/strategy.py
epde/optimizers/moeadd/__init__.py
epde/optimizers/moeadd/moeadd.py
epde/optimizers/moeadd/population_constr.py
epde/optimizers/moeadd/solution_template.py
epde/optimizers/moeadd/strategy.py
epde/optimizers/moeadd/strategy_elems.py
epde/optimizers/moeadd/supplementary.py
epde/optimizers/moeadd/vis.py
epde/optimizers/single_criterion/__init__.py
epde/optimizers/single_criterion/ea_stop_conds.py
epde-1.2.17.dist-info/LICENSE.txt
epde-1.2.17.dist-info/METADATA
epde-1.2.17.dist-info/WHEEL
epde-1.2.17.dist-info/top_level.txt
epde-1.2.17.dist-info/RECORD
