Metadata-Version: 2.1
Name: epde
Version: 1.2.17
Summary: Data-driven dynamical system and differential equations discovery framework
Author: Mikhail Maslyaev
Author-email: miklemas@list.ru
Classifier: Development Status :: 3 - Alpha
Classifier: Programming Language :: Python :: 3
Classifier: License :: OSI Approved :: MIT License
Classifier: Operating System :: OS Independent
Requires-Python: >=3.8
License-File: LICENSE.txt
